setup.py
lib/__init__.py
lib/oauth.py
pesapal.egg-info/PKG-INFO
pesapal.egg-info/SOURCES.txt
pesapal.egg-info/dependency_links.txt
pesapal.egg-info/top_level.txt
pesapal.egg-info/zip-safe