Metadata-Version: 1.0
Name: pesapal
Version: 0.0.3
Summary: Pesapal API python library.
Home-page: https://github.com/kelonye/python-pesapal
Author: Mitchel Kelonye
Author-email: kelonyemitchel@gmail.com
License: MIT License
Platform: UNKNOWN
